prettier_unittest/__init__.py
prettier_unittest-0.1.data/scripts/prettier-unittest
prettier_unittest-0.1.dist-info/LICENSE
prettier_unittest-0.1.dist-info/METADATA
prettier_unittest-0.1.dist-info/WHEEL
prettier_unittest-0.1.dist-info/top_level.txt
prettier_unittest-0.1.dist-info/RECORD
