Metadata-Version: 2.1
Name: prettier-unittest
Version: 0.1
Summary: A small package to easily setup unittests and have a better rendering
Home-page: https://github.com/SpartanPlume/PrettierUnittestPython
Author: Spartan Plu,e
Author-email: spartan.plume@gmail.com
License: MIT
Keywords: prettier pretty color unittest unit test
Platform: UNKNOWN
Requires-Dist: Pygments
Requires-Dist: blessings
